CHANGES.rst
LICENSE
MANIFEST.in
README.rst
setup.cfg
setup.py
py_socketio_client/__init__.py
py_socketio_client/exceptions.py
py_socketio_client/heartbeats.py
py_socketio_client/logs.py
py_socketio_client/namespaces.py
py_socketio_client/parsers.py
py_socketio_client/symmetries.py
py_socketio_client/transports.py
py_socketio_client.egg-info/PKG-INFO
py_socketio_client.egg-info/SOURCES.txt
py_socketio_client.egg-info/dependency_links.txt
py_socketio_client.egg-info/not-zip-safe
py_socketio_client.egg-info/requires.txt
py_socketio_client.egg-info/top_level.txt
py_socketio_client/tests/__init__.py