Metadata-Version: 1.1
Name: py-socketio-client
Version: 0.0.1
Summary: A socket.io client library
Home-page: https://github.com/halilozercan/py-socketio-client
Author: Roy Hyunjin Han, Halil Ozercan
Author-email: halilozercan@gmail.com
License: MIT
Keywords: socket.io node.js
Platform: UNKNOWN
Classifier: Intended Audience :: Developers
Classifier: Programming Language :: Python
Classifier: License :: OSI Approved :: MIT License
Classifier: Development Status :: 5 - Production/Stable
